MANIFEST.in
README.rst
pyproject.toml
setup.cfg
setup.py
adapya/__init__.py
adapya/adabas/scripts/asmfreader.py
adapya/adabas/scripts/dblist.py
adapya/adabas/scripts/mproc.py
adapya/adabas/scripts/search.py
adapya/adabas/scripts/ticker.py
adapya/adabas/__init__.py
adapya/adabas/adaerror.py
adapya/adabas/api.py
adapya/adabas/asmfrec.py
adapya/adabas/asmfrec13.py
adapya/adabas/asmfrec14.py
adapya/adabas/asmfrec15.py
adapya/adabas/asmfrec16.py
adapya/adabas/asmfrec21.py
adapya/adabas/asmfrec31.py
adapya/adabas/fields.py
adapya/adabas/metadata.py
adapya/adabas/sysdic.py
adapya/adabas/doc/conf.py
adapya/adabas/doc/_static/image002.jpg
adapya/adabas/doc/_static/image004.jpg
adapya/adabas/doc/_static/image006.jpg
adapya/adabas/doc/_static/image007.gif
adapya/adabas/scripts/__init__.py
adapya/adabas/scripts/asmfreader.py
adapya/adabas/scripts/dblist.py
adapya/adabas/scripts/empltel.py
adapya/adabas/scripts/mproc.py
adapya/adabas/scripts/readfdt.py
adapya/adabas/scripts/search.py
adapya/adabas/scripts/ticker.py
adapya/adabas/scripts/updater.py
adapya_adabas.egg-info/PKG-INFO
adapya_adabas.egg-info/SOURCES.txt
adapya_adabas.egg-info/dependency_links.txt
adapya_adabas.egg-info/namespace_packages.txt
adapya_adabas.egg-info/not-zip-safe
adapya_adabas.egg-info/requires.txt
adapya_adabas.egg-info/top_level.txt